flange/__init__.py
flange/cfg.py
flange/data.py
flange/dbengine.py
flange/httpjson.py
flange/iterutils.py
flange/model.py
flange/source.py
flange/url_scheme_python.py
flange/util/__init__.py
flange-1.0.1.dist-info/LICENSE
flange-1.0.1.dist-info/METADATA
flange-1.0.1.dist-info/WHEEL
flange-1.0.1.dist-info/top_level.txt
flange-1.0.1.dist-info/RECORD
